[
  {
    "source": "craigslist",
    "source_id": "7920642635",
    "source_url": "https://austin.craigslist.org/apa/d/austin-1st-floor-bark-park-stainless/7920642635.html",
    "title": "1st floor, Bark Park, Stainless steel appliances$7108300 North Interstate Highway 35, Austin, TX",
    "price": 710.0,
    "address": "8300 North Interstate Highway 35, Austin, TX",
    "listing_type": "apartment",
    "description": null,
    "images": [],
    "raw_data": {},
    "deal_score": 80,
    "deal_classification": "STEAL"
  },
  {
    "source": "craigslist",
    "source_id": "7925296404",
    "source_url": "https://austin.craigslist.org/apa/d/austin-parkside-paradise-your-front/7925296404.html",
    "title": "Parkside Paradise: Your Front Door Opens to 50 Miles of Scenic Hiking$850",
    "price": 850.0,
    "address": "",
    "listing_type": "apartment",
    "description": null,
    "images": [],
    "raw_data": {},
    "deal_score": 80,
    "deal_classification": "STEAL"
  },
  {
    "source": "craigslist",
    "source_id": "7924686412",
    "source_url": "https://austin.craigslist.org/apa/d/austin-upgrade-your-lifestyle-stunning/7924686412.html",
    "title": "Upgrade your lifestyle: Stunning 1 BR, 680 Sq Ft homes.$849Austin - North Park Shopping Center",
    "price": 849.0,
    "address": "Austin - North Park Shopping Center",
    "listing_type": "apartment",
    "description": null,
    "images": [],
    "raw_data": {},
    "deal_score": 80,
    "deal_classification": "STEAL"
  },
  {
    "source": "craigslist",
    "source_id": "7924354670",
    "source_url": "https://austin.craigslist.org/apa/d/cedar-park-walk-in-closets-gated-gym/7924354670.html",
    "title": "Walk-in closets - Gated - Gym - Pool - Near dining and shopping!$1,115Cedar Park",
    "price": 1115.0,
    "address": "Cedar Park",
    "listing_type": "apartment",
    "description": null,
    "images": [],
    "raw_data": {},
    "deal_score": 80,
    "deal_classification": "STEAL"
  },
  {
    "source": "craigslist",
    "source_id": "7924833981",
    "source_url": "https://austin.craigslist.org/apa/d/austin-on-site-laundry-facility/7924833981.html",
    "title": "On-Site Laundry Facility, Stainless Steel Appliances, 1st floor$7758300 North Interstate Highway 35, Austin, TX",
    "price": 775.0,
    "address": "8300 North Interstate Highway 35, Austin, TX",
    "listing_type": "apartment",
    "description": null,
    "images": [],
    "raw_data": {},
    "deal_score": 80,
    "deal_classification": "STEAL"
  },
  {
    "source": "craigslist",
    "source_id": "7922975356",
    "source_url": "https://austin.craigslist.org/apa/d/round-rock-vive-con-comodidad-sin/7922975356.html",
    "title": "\u00a1Vive con comodidad: sin contrato de arrendamiento, sin dep\u00f3sito!$3701201 Louis Henna Blvd, Round Rock, TX",
    "price": 370.0,
    "address": "1201 Louis Henna Blvd, Round Rock, TX",
    "listing_type": "apartment",
    "description": null,
    "images": [],
    "raw_data": {},
    "deal_score": 80,
    "deal_classification": "STEAL"
  },
  {
    "source": "craigslist",
    "source_id": "7924704530",
    "source_url": "https://austin.craigslist.org/apa/d/austin-your-sanctuary-awaits-br-ba-and/7924704530.html",
    "title": "Your sanctuary awaits: 1 BR, 1 BA, and much more!$899Austin - North Park Shopping Center",
    "price": 899.0,
    "address": "Austin - North Park Shopping Center",
    "listing_type": "apartment",
    "description": null,
    "images": [],
    "raw_data": {},
    "deal_score": 80,
    "deal_classification": "STEAL"
  },
  {
    "source": "craigslist",
    "source_id": "7923952311",
    "source_url": "https://austin.craigslist.org/apa/d/leander-all-inclusive-affordable-living/7923952311.html",
    "title": "All-Inclusive Affordable Living - No Hidden Fees$3605210 183A Toll Rd, Cedar Park, TX",
    "price": 360.0,
    "address": "5210 183A Toll Rd, Cedar Park, TX",
    "listing_type": "apartment",
    "description": null,
    "images": [],
    "raw_data": {},
    "deal_score": 80,
    "deal_classification": "STEAL"
  },
  {
    "source": "craigslist",
    "source_id": "7920265232",
    "source_url": "https://austin.craigslist.org/apa/d/austin-furnished-apartment-studio-under/7920265232.html",
    "title": "Furnished Apartment, Studio under $1000, Elevator$8208300 North Interstate Highway 35, Austin, TX",
    "price": 820.0,
    "address": "8300 North Interstate Highway 35, Austin, TX",
    "listing_type": "apartment",
    "description": null,
    "images": [],
    "raw_data": {},
    "deal_score": 80,
    "deal_classification": "STEAL"
  },
  {
    "source": "craigslist",
    "source_id": "7920592887",
    "source_url": "https://austin.craigslist.org/apa/d/austin-south-austin-1bd-1ba-apartment/7920592887.html",
    "title": "South Austin 1BD/1BA Apartment + Washer/Dryer in Unit$1,030Austin",
    "price": 1030.0,
    "address": "Austin",
    "listing_type": "apartment",
    "description": null,
    "images": [],
    "raw_data": {},
    "deal_score": 80,
    "deal_classification": "STEAL"
  },
  {
    "source": "craigslist",
    "source_id": "7923236910",
    "source_url": "https://austin.craigslist.org/apa/d/austin-covered-rv-on-the-river/7923236910.html",
    "title": "Covered RV on the River$699Del Valle, hwy 71",
    "price": 699.0,
    "address": "Del Valle, hwy 71",
    "listing_type": "apartment",
    "description": null,
    "images": [],
    "raw_data": {},
    "deal_score": 80,
    "deal_classification": "STEAL"
  },
  {
    "source": "craigslist",
    "source_id": "7925273834",
    "source_url": "https://austin.craigslist.org/apa/d/round-rock-live-bold-authentic-nestled/7925273834.html",
    "title": "Live Bold & Authentic \u2013 Nestled in a Vibrant La Frontera Neighborhood!$1,010Round Rock, Tx",
    "price": 1010.0,
    "address": "Round Rock, Tx",
    "listing_type": "apartment",
    "description": null,
    "images": [],
    "raw_data": {},
    "deal_score": 80,
    "deal_classification": "STEAL"
  },
  {
    "source": "craigslist",
    "source_id": "7916318488",
    "source_url": "https://austin.craigslist.org/apa/d/round-rock-stylish-new-apartments-in/7916318488.html",
    "title": "\ud83d\udea8 Stylish New Apartments in Round Rock \u2013 Enjoy 8 Weeks Free Rent! \ud83c\udfd9$1,066Round Rock",
    "price": 1066.0,
    "address": "Round Rock",
    "listing_type": "apartment",
    "description": null,
    "images": [],
    "raw_data": {},
    "deal_score": 80,
    "deal_classification": "STEAL"
  },
  {
    "source": "craigslist",
    "source_id": "7916328809",
    "source_url": "https://austin.craigslist.org/apa/d/leander-enjoy-months-at-half-rent-pet/7916328809.html",
    "title": "\ud83c\udff7\ufe0f Enjoy 4 Months at Half Rent \u2013 Pet-Friendly Homes in Leander!$1,015Leander",
    "price": 1015.0,
    "address": "Leander",
    "listing_type": "apartment",
    "description": null,
    "images": [],
    "raw_data": {},
    "deal_score": 80,
    "deal_classification": "STEAL"
  },
  {
    "source": "craigslist",
    "source_id": "7921270242",
    "source_url": "https://austin.craigslist.org/apa/d/georgetown-move-in-special-enjoy-12/7921270242.html",
    "title": "\ud83c\udf89 Move-In Special! Enjoy 12 Weeks FREE at Modern Georgetown Apartment$1,105Georgetown",
    "price": 1105.0,
    "address": "Georgetown",
    "listing_type": "apartment",
    "description": null,
    "images": [],
    "raw_data": {},
    "deal_score": 80,
    "deal_classification": "STEAL"
  },
  {
    "source": "craigslist",
    "source_id": "7921219583",
    "source_url": "https://austin.craigslist.org/apa/d/georgetown-free-weeks-just-opened-pet/7921219583.html",
    "title": "\ud83c\udfe1 FREE 8 Weeks! Just Opened Pet-Friendly Apartments in Georgetown$1,077Georgetown",
    "price": 1077.0,
    "address": "Georgetown",
    "listing_type": "apartment",
    "description": null,
    "images": [],
    "raw_data": {},
    "deal_score": 80,
    "deal_classification": "STEAL"
  },
  {
    "source": "craigslist",
    "source_id": "7916517069",
    "source_url": "https://austin.craigslist.org/apa/d/cedar-park-roomy-studios-in-cedar-park/7916517069.html",
    "title": "\ud83c\udfe1 Roomy Studios in Cedar Park \u2013 Perfect for You and Your Pet! \ud83d\udc3e$995Cedar Park",
    "price": 995.0,
    "address": "Cedar Park",
    "listing_type": "apartment",
    "description": null,
    "images": [],
    "raw_data": {},
    "deal_score": 80,
    "deal_classification": "STEAL"
  },
  {
    "source": "craigslist",
    "source_id": "7917529938",
    "source_url": "https://austin.craigslist.org/apa/d/austin-west-austin-living-months-rent/7917529938.html",
    "title": "\ud83c\udfd9\ufe0f West Austin Living \u2013 2 Months Rent FREE! Pet-Friendly Homes$1,095SW Austin",
    "price": 1095.0,
    "address": "SW Austin",
    "listing_type": "apartment",
    "description": null,
    "images": [],
    "raw_data": {},
    "deal_score": 80,
    "deal_classification": "STEAL"
  },
  {
    "source": "craigslist",
    "source_id": "7925270468",
    "source_url": "https://austin.craigslist.org/apa/d/austin-off-street-parking-hardwood/7925270468.html",
    "title": "Off Street Parking, Hardwood Floors, 24-Hour Fitness Center$8298300 North Interstate Highway 35, Austin, TX",
    "price": 829.0,
    "address": "8300 North Interstate Highway 35, Austin, TX",
    "listing_type": "apartment",
    "description": null,
    "images": [],
    "raw_data": {},
    "deal_score": 80,
    "deal_classification": "STEAL"
  },
  {
    "source": "craigslist",
    "source_id": "7923268751",
    "source_url": "https://austin.craigslist.org/apa/d/austin-near-class-were-only-short/7923268751.html",
    "title": "Near class! We're only a short distance from campus! 2 bed / 1 bath$999Austin - North Park Shopping Center",
    "price": 999.0,
    "address": "Austin - North Park Shopping Center",
    "listing_type": "apartment",
    "description": null,
    "images": [],
    "raw_data": {},
    "deal_score": 80,
    "deal_classification": "STEAL"
  }
]